mongomodel/__init__.py
mongomodel/document.py
mongomodel/field.py
mongomodel/keywords.py
mongomodel/queryset.py
mongomodel/tools.py
mongomodel-0.5.3.dist-info/WHEEL
mongomodel-0.5.3.dist-info/METADATA
mongomodel-0.5.3.dist-info/RECORD
