Metadata-Version: 2.1
Name: mongomodel
Version: 0.5.3
Summary: Tiny mongodb orm document oriented
License: MIT
Author: Sébastien NICOLET
Author-email: snicolet@student.42.fr
Requires-Python: >=3.7,<4.0
Classifier: License :: OSI Approved :: MIT License
Classifier: Programming Language :: Python :: 3
Classifier: Programming Language :: Python :: 3.7
Classifier: Programming Language :: Python :: 3.8
Classifier: Programming Language :: Python :: 3.9
Requires-Dist: pymongo (>=3.10.1,<4.0.0)
